cs251simulator_compiler/__init__.py
cs251simulator_compiler/__main__.py
cs251simulator_compiler/model.py
cs251simulator_compiler/parser.out
cs251simulator_compiler/parser.py
cs251simulator_compiler/parsetab.py
cs251simulator_compiler-0.1.3.dist-info/METADATA
cs251simulator_compiler-0.1.3.dist-info/WHEEL
cs251simulator_compiler-0.1.3.dist-info/entry_points.txt
cs251simulator_compiler-0.1.3.dist-info/RECORD
