Metadata-Version: 2.4
Name: cs251simulator-compiler
Version: 0.1.3
Requires-Python: >=3.10
Requires-Dist: ply>=3.11
Requires-Dist: pydantic>=2.10.5
Requires-Dist: typer>=0.15.1
